{
  "score": 92,
  "verdict": "Minor Revisions",
  "strengths": [
    "Clear structure with dated sections",
    "Specific details and numbers provided",
    "All required sections filled",
    "Clear language used throughout the document"
  ],
  "weaknesses": [
    "Some sections could be more concise",
    "A few sentences are slightly unclear",
    "No clear summary or introduction"
  ],
  "top_fixes": [
    "Add a brief introduction to summarize the document's purpose",
    "Condense sections with excessive detail",
    "Clarify sentences with ambiguous wording"
  ],
  "blocking_issues": []
}